recaptchav2solver/__init__.py
recaptchav2solver/solver.py
recaptchav2solver-1.2.0.dist-info/LICENSE
recaptchav2solver-1.2.0.dist-info/METADATA
recaptchav2solver-1.2.0.dist-info/WHEEL
recaptchav2solver-1.2.0.dist-info/top_level.txt
recaptchav2solver-1.2.0.dist-info/RECORD
