Metadata-Version: 2.1
Name: recaptchav2solver
Version: 1.2.0
Summary: A Python package to solve reCAPTCHA audio challenges using Selenium and SpeechRecognition
Home-page: https://github.com/lucassoares-eng/python-recaptchav2solver
Author: Lucas Soares
Author-email: lucasjs.eng@gmail.com
Classifier: Programming Language :: Python :: 3
Classifier: License :: OSI Approved :: MIT License
Classifier: Operating System :: OS Independent
Requires-Python: >=3.6
License-File: LICENSE
Requires-Dist: requests ==2.31.0
Requires-Dist: selenium ==4.27.1
Requires-Dist: speechrecognition ==3.14.0
Requires-Dist: pydub ==0.25.1
